cpick/__init__.py
cpick/__main__.py
cpick/action.py
cpick/draw.py
cpick/event.py
cpick/keys.py
cpick/screen.py
cpick-0.0.7.dist-info/LICENSE
cpick-0.0.7.dist-info/METADATA
cpick-0.0.7.dist-info/WHEEL
cpick-0.0.7.dist-info/entry_points.txt
cpick-0.0.7.dist-info/top_level.txt
cpick-0.0.7.dist-info/RECORD
