Metadata-Version: 2.1
Name: cpick
Version: 0.0.7
Summary: Curses List Picker
Home-page: https://github.com/tslight/cpick
Author: Toby Slight
Author-email: tslight@pm.me
License: UNKNOWN
Platform: UNKNOWN
Classifier: Programming Language :: Python :: 3
Classifier: License :: OSI Approved :: ISC License (ISCL)
Classifier: Operating System :: OS Independent
